check_install/__init__.py
check_install-0.1.1.dist-info/METADATA
check_install-0.1.1.dist-info/WHEEL
check_install-0.1.1.dist-info/licenses/LICENSE
check_install-0.1.1.dist-info/RECORD
