Metadata-Version: 2.4
Name: check-install
Version: 0.1.1
Summary: Attempts to verify and auto-install missing Python packages at runtime or startup.
Project-URL: Homepage, https://github.com/daytonjones/check-install
Project-URL: Source, https://github.com/daytonjones/check-install
Project-URL: Issues, https://github.com/daytonjones/check-install/issues
Author: Dayton Jones
License: MIT
License-File: LICENSE
Keywords: auto-install,dependency,helper,import,missing,pip,preflight,runtime
Classifier: Development Status :: 4 - Beta
Classifier: Intended Audience :: Developers
Classifier: License :: OSI Approved :: MIT License
Classifier: Operating System :: OS Independent
Classifier: Programming Language :: Python :: 3
Classifier: Programming Language :: Python :: 3.9
Classifier: Programming Language :: Python :: 3.10
Classifier: Programming Language :: Python :: 3.11
Classifier: Programming Language :: Python :: 3.12
Classifier: Topic :: Software Development :: Build Tools
Classifier: Topic :: Utilities
Requires-Python: >=3.9
